{
  "main": {
    "id": "0dab366648896a9b",
    "type": "split",
    "children": [
      {
        "id": "88efe2c03047e8bd",
        "type": "tabs",
        "children": [
          {
            "id": "7ef170f8dfaf12d5",
            "type": "leaf",
            "state": {
              "type": "markdown",
              "state": {
                "file": "Happy Game/开发阶段/生命/003-程序化生成系统.md",
                "mode": "source",
                "source": false
              },
              "icon": "lucide-file",
              "title": "003-程序化生成系统"
            }
          }
        ]
      }
    ],
    "direction": "vertical"
  },
  "left": {
    "id": "3554209de5d41238",
    "type": "split",
    "children": [
      {
        "id": "84790708d07e2310",
        "type": "tabs",
        "children": [
          {
            "id": "9fd2dd038a914461",
            "type": "leaf",
            "state": {
              "type": "file-explorer",
              "state": {
                "sortOrder": "alphabetical",
                "autoReveal": false
              },
              "icon": "lucide-folder-closed",
              "title": "文件列表"
            }
          },
          {
            "id": "2017d33597c7bead",
            "type": "leaf",
            "state": {
              "type": "search",
              "state": {
                "query": "",
                "matchingCase": false,
                "explainSearch": false,
                "collapseAll": false,
                "extraContext": false,
                "sortOrder": "alphabetical"
              },
              "icon": "lucide-search",
              "title": "搜索"
            }
          },
          {
            "id": "3b5b6a59cb843d9d",
            "type": "leaf",
            "state": {
              "type": "bookmarks",
              "state": {},
              "icon": "lucide-bookmark",
              "title": "书签"
            }
          }
        ]
      }
    ],
    "direction": "horizontal",
    "width": 300
  },
  "right": {
    "id": "6f0207a97ef0afb2",
    "type": "split",
    "children": [
      {
        "id": "0f6f2e4cc972feff",
        "type": "tabs",
        "children": [
          {
            "id": "66487a616be19b33",
            "type": "leaf",
            "state": {
              "type": "backlink",
              "state": {
                "file": "未命名 1.base",
                "collapseAll": false,
                "extraContext": false,
                "sortOrder": "alphabetical",
                "showSearch": false,
                "searchQuery": "",
                "backlinkCollapsed": false,
                "unlinkedCollapsed": true
              },
              "icon": "links-coming-in",
              "title": "未命名 1 的反向链接列表"
            }
          },
          {
            "id": "97cf603aec063438",
            "type": "leaf",
            "state": {
              "type": "outgoing-link",
              "state": {
                "file": "参考文档/001-核心系统设计参考-20260609/002-NPC心智模型与心理学参考.md",
                "linksCollapsed": false,
                "unlinkedCollapsed": true
              },
              "icon": "links-going-out",
              "title": "002-NPC心智模型与心理学参考 的出链列表"
            }
          },
          {
            "id": "f7c49a5f1dc52aa3",
            "type": "leaf",
            "state": {
              "type": "tag",
              "state": {
                "sortOrder": "frequency",
                "useHierarchy": true,
                "showSearch": false,
                "searchQuery": ""
              },
              "icon": "lucide-tags",
              "title": "标签"
            }
          },
          {
            "id": "33fc2d3f9f05792e",
            "type": "leaf",
            "state": {
              "type": "all-properties",
              "state": {
                "sortOrder": "frequency",
                "showSearch": false,
                "searchQuery": ""
              },
              "icon": "lucide-archive",
              "title": "添加笔记属性"
            }
          },
          {
            "id": "5126de9cccdeb4d3",
            "type": "leaf",
            "state": {
              "type": "outline",
              "state": {
                "file": "未命名 1.base",
                "followCursor": false,
                "showSearch": false,
                "searchQuery": ""
              },
              "icon": "lucide-list",
              "title": "未命名 1 的大纲"
            }
          },
          {
            "id": "e0421fc6f88c5180",
            "type": "leaf",
            "state": {
              "type": "markdown",
              "state": {
                "file": "Happy Game/想法/WoW World/生命/神明/NPC信仰系统.md",
                "mode": "source",
                "source": false
              },
              "icon": "lucide-file",
              "title": "NPC信仰系统"
            }
          }
        ],
        "currentTab": 5
      }
    ],
    "direction": "horizontal",
    "width": 365.5,
    "collapsed": true
  },
  "left-ribbon": {
    "hiddenItems": {
      "graph:查看关系图谱": false,
      "switcher:打开快速切换": false,
      "canvas:新建白板": false,
      "daily-notes:打开/创建今天的日记": false,
      "templates:插入模板": false,
      "command-palette:打开命令面板": false,
      "bases:新建数据库": false
    }
  },
  "active": "7ef170f8dfaf12d5",
  "lastOpenFiles": [
    "Happy Game/开发阶段/生命/011-玩家.md.tmp.35704.eab152361d33",
    "Happy Game/开发阶段/生命/009-植物.md.tmp.35704.9041ff98f0da",
    "Happy Game/开发阶段/生命/008-亡灵.md.tmp.35704.9e3880fd7948",
    "Happy Game/开发阶段/生命/007-怪物.md.tmp.35704.62d1be283268",
    "Happy Game/开发阶段/生命/010-神明与信仰.md.tmp.35704.ebbdc1835932",
    "Happy Game/开发阶段/生命/006-灵兽.md.tmp.35704.d70f8d71e3a6",
    "Happy Game/开发阶段/生命/005-动物.md.tmp.35704.787f2cf4439f",
    "Happy Game/开发阶段/生命/012-繁衍系统.md.tmp.35704.560e10b514c1",
    "Happy Game/开发阶段/生命/002-种族与特质.md",
    "Happy Game/开发阶段/生命/001-生命总纲.md",
    "Happy Game/开发阶段/生命/004-身体状态与生命过程.md.tmp.35704.bdb0895d7d5f",
    "Happy Game/开发阶段/生命/003-程序化生成系统.md.tmp.35704.4155bd1bf0de",
    "Change/CHG-010-世界生成v3重构-20260611.md",
    "Change/CHG-011-生命系统v1.0设计-20260611.md",
    "Happy Game/开发阶段/世界生成/007-体素设计决策.md",
    "Happy Game/开发阶段/世界生成/006-交通网络.md",
    "Happy Game/开发阶段/世界生成/004-聚落生成.md",
    "Happy Game/开发阶段/生命/011-玩家.md",
    "Happy Game/开发阶段/生命/001-生命总纲.md.tmp.35704.1be37c4a1c73",
    "Happy Game/开发阶段/世界生成/008-NPC初始化与历史模拟.md",
    "Happy Game/开发阶段/世界生成/001-世界生成总流程.md",
    "Happy Game/开发阶段/世界生成/002-自然景观.md",
    "Happy Game/开发阶段/生命/012-繁衍系统.md",
    "Happy Game/开发阶段/生命/004-身体状态与生命过程.md",
    "Happy Game/开发阶段/生命/005-动物.md",
    "Happy Game/开发阶段/生命/003-程序化生成系统.md",
    "Happy Game/开发阶段/生命/006-灵兽.md",
    "Happy Game/想法/WoW World/生命/怪物.md",
    "Happy Game/开发阶段/生命/010-神明与信仰.md",
    "Happy Game/开发阶段/生命/009-植物.md",
    "Happy Game/开发阶段/生命/008-亡灵.md",
    "Happy Game/开发阶段/生命/007-怪物.md",
    "Happy Game/开发阶段/生命/README.md",
    "Happy Game/想法/WoW World/生命/造物.md",
    "Happy Game/想法/WoW World/生命/动物.md",
    "Happy Game/想法/WoW World/基质.md",
    "Happy Game/想法/WoW World/生命/NPC/角色处理对象时的心理作用.canvas"
  ]
}